eagle_helper/__init__.py
eagle_helper/config.py
eagle_helper/cli/__init__.py
eagle_helper/cli/__main__.py
eagle_helper/cli/plugin_init.py
eagle_helper/cli/plugin_walk.py
eagle_helper/coms/files.py
eagle_helper/coms/locales.py
eagle_helper/coms/manifest.py
eagle_helper/etc/__init__.py
eagle_helper/etc/git.py
eagle_helper/i18n/zh_CN.json
eagle_helper-0.1.1.dist-info/METADATA
eagle_helper-0.1.1.dist-info/WHEEL
eagle_helper-0.1.1.dist-info/entry_points.txt
eagle_helper-0.1.1.dist-info/licenses/LICENSE
eagle_helper-0.1.1.dist-info/RECORD
