Metadata-Version: 2.4
Name: eagle-helper
Version: 0.1.1
Summary: Eagle.cool Helper for plugin initialization, i18n efforts, and more.
Author-email: ZackaryW <gitzackw@gmail.com>
License-File: LICENSE
Requires-Python: >=3.8
Requires-Dist: click>=8.1.8
